flightplandb/__init__.py
flightplandb/api.py
flightplandb/datatypes.py
flightplandb/exceptions.py
flightplandb/internal.py
flightplandb/nav.py
flightplandb/plan.py
flightplandb/py.typed
flightplandb/tags.py
flightplandb/user.py
flightplandb/weather.py
flightplandb-0.8.2.dist-info/LICENSE
flightplandb-0.8.2.dist-info/METADATA
flightplandb-0.8.2.dist-info/WHEEL
flightplandb-0.8.2.dist-info/top_level.txt
flightplandb-0.8.2.dist-info/RECORD
