Metadata-Version: 2.1
Name: flightplandb
Version: 0.8.2
Summary: Python wrapper for the Flight Plan Database API
Author-email: PH-KDX <smtp.python.email.sender@gmail.com>
License: GPL v3
Project-URL: Homepage, https://github.com/PH-KDX/flightplandb-py/
Project-URL: Documentation, https://flightplandb-py.readthedocs.io/
Project-URL: Issue tracker, https://github.com/PH-KDX/flightplandb-py/issues
Project-URL: Changelog, https://github.com/PH-KDX/flightplandb-py/blob/main/CHANGELOG.rst
Classifier: License :: OSI Approved :: GNU General Public License v3 (GPLv3)
Classifier: Intended Audience :: Developers
Classifier: Natural Language :: English
Classifier: Programming Language :: Python :: 3.8
Classifier: Programming Language :: Python :: 3.9
Classifier: Programming Language :: Python :: 3.10
Classifier: Programming Language :: Python :: 3.10
Classifier: Programming Language :: Python :: 3.11
Classifier: Programming Language :: Python :: 3.12
Classifier: Operating System :: OS Independent
Classifier: Topic :: Internet
Classifier: Topic :: Software Development :: Libraries
Classifier: Topic :: Software Development :: Libraries :: Python Modules
Classifier: Topic :: Utilities
Classifier: Topic :: Games/Entertainment :: Simulation
Requires-Python: >=3.8
License-File: LICENSE
Requires-Dist: python-dateutil ~=2.8.2
Requires-Dist: aiohttp >=3.5.2 ; python_version < "3.11"
Requires-Dist: aiohttp >=3.8.4 ; python_version >= "3.11"
Provides-Extra: dev
Requires-Dist: pre-commit ; extra == 'dev'
Provides-Extra: docs
Requires-Dist: Sphinx ==6.2.1 ; extra == 'docs'
Requires-Dist: sphinx-rtd-theme ==1.2.0 ; extra == 'docs'
Provides-Extra: test
Requires-Dist: pytest ~=7.3.1 ; extra == 'test'
Requires-Dist: pytest-socket ~=0.6.0 ; extra == 'test'
Requires-Dist: pytest-asyncio ~=0.21.0 ; extra == 'test'
